msgspec/msgpack.py
msgspec/msgpack.pyi
msgspec/__init__.pyi
msgspec/_version.py
msgspec/__init__.py
msgspec/_core.cpython-312-darwin.so
msgspec/yaml.py
msgspec/structs.py
msgspec/inspect.py
msgspec/json.pyi
msgspec/_json_schema.py
msgspec/py.typed
msgspec/structs.pyi
msgspec/json.py
msgspec/_utils.py
msgspec/toml.py
msgspec_x/__init__.py
msgspec_x-0.20.0.dist-info/RECORD
msgspec_x-0.20.0.dist-info/WHEEL
msgspec_x-0.20.0.dist-info/top_level.txt
msgspec_x-0.20.0.dist-info/METADATA
msgspec_x-0.20.0.dist-info/licenses/LICENSE
