Metadata-Version: 2.4
Name: msgspec-x
Version: 0.20.0
Summary: A community-driven fork of msgspec: fast serialization and validation library with builtin support for JSON, MessagePack, YAML, and TOML. Provides dual namespace architecture - 'msgspec' for full compatibility and 'msgspec_x' for extended features.
Home-page: https://nightsailer.github.io/msgspec-x/
Maintainer: Night Sailer
Maintainer-email: nightsailer@gmail.com
License: BSD
Project-URL: Documentation, https://nightsailer.github.io/msgspec-x/
Project-URL: Source, https://github.com/nightsailer/msgspec-x/
Project-URL: Issue Tracker, https://github.com/nightsailer/msgspec-x/issues
Keywords: JSON msgpack MessagePack TOML YAML serialization validation schema fork community
Classifier: License :: OSI Approved :: BSD License
Classifier: Development Status :: 4 - Beta
Classifier: Programming Language :: Python :: 3.9
Classifier: Programming Language :: Python :: 3.10
Classifier: Programming Language :: Python :: 3.11
Classifier: Programming Language :: Python :: 3.12
Classifier: Programming Language :: Python :: 3.13
Requires-Python: >=3.9
License-File: LICENSE
Provides-Extra: yaml
Requires-Dist: pyyaml; extra == "yaml"
Provides-Extra: toml
Requires-Dist: tomli; python_version < "3.11" and extra == "toml"
Requires-Dist: tomli_w; extra == "toml"
Provides-Extra: doc
Requires-Dist: sphinx; extra == "doc"
Requires-Dist: furo; extra == "doc"
Requires-Dist: sphinx-copybutton; extra == "doc"
Requires-Dist: sphinx-design; extra == "doc"
Requires-Dist: ipython; extra == "doc"
Provides-Extra: test
Requires-Dist: pytest; extra == "test"
Requires-Dist: msgpack; extra == "test"
Requires-Dist: attrs; extra == "test"
Requires-Dist: eval-type-backport; python_version < "3.10" and extra == "test"
Requires-Dist: pyyaml; extra == "test"
Requires-Dist: tomli; python_version < "3.11" and extra == "test"
Requires-Dist: tomli_w; extra == "test"
Provides-Extra: dev
Requires-Dist: pre-commit; extra == "dev"
Requires-Dist: coverage; extra == "dev"
Requires-Dist: mypy; extra == "dev"
Requires-Dist: pyright; extra == "dev"
Requires-Dist: sphinx; extra == "dev"
Requires-Dist: furo; extra == "dev"
Requires-Dist: sphinx-copybutton; extra == "dev"
Requires-Dist: sphinx-design; extra == "dev"
Requires-Dist: ipython; extra == "dev"
Requires-Dist: pytest; extra == "dev"
Requires-Dist: msgpack; extra == "dev"
Requires-Dist: attrs; extra == "dev"
Requires-Dist: eval-type-backport; python_version < "3.10" and extra == "dev"
Requires-Dist: pyyaml; extra == "dev"
Requires-Dist: tomli; python_version < "3.11" and extra == "dev"
Requires-Dist: tomli_w; extra == "dev"
Dynamic: classifier
Dynamic: description
Dynamic: description-content-type
Dynamic: home-page
Dynamic: keywords
Dynamic: license
Dynamic: license-file
Dynamic: maintainer
Dynamic: maintainer-email
Dynamic: project-url
Dynamic: provides-extra
Dynamic: requires-python
Dynamic: summary
